edfpy/__init__.py
edfpy/blob.py
edfpy/cached_property.py
edfpy/channel.py
edfpy/channel_base.py
edfpy/derivation.py
edfpy/field.py
edfpy/header.py
edfpy/label.py
edfpy/notation.py
edfpy/plotting.py
edfpy/reader.py
edfpy/version.py
edfpy-0.2.2.dist-info/LICENSE
edfpy-0.2.2.dist-info/METADATA
edfpy-0.2.2.dist-info/WHEEL
edfpy-0.2.2.dist-info/top_level.txt
edfpy-0.2.2.dist-info/RECORD
