Metadata-Version: 2.1
Name: edfpy
Version: 0.2.2
Summary: Lean EDF Reader
Author: Justus Schwabedal, John Snyder
Maintainer: Justus Schwabedal
Maintainer-email: jschwabedal@gmail.com
License: UNKNOWN
Platform: UNKNOWN
Classifier: Programming Language :: Python :: 3
Classifier: License :: OSI Approved :: MIT License
Classifier: Operating System :: OS Independent
Requires-Python: >=3.8
License-File: LICENSE
Requires-Dist: numpy (>=1.14.1)
Requires-Dist: cached-property (>=1.5.2)
